[{"Rank": "1", "Player": "Michael Jordan", "From": "1985", "To": "2003", "Games": "1072", "Minutes Played Per Game": "38.3", "Points Per Game": "30.1", "Total Rebounds Per Game": "6.2", "Assists Per Game": "5.3", "Steals Per Game": "2.3", "Blocks Per Game": "0.8", "Field Goal Percentage": ".497", "3-Point Field Goal Percentage": ".327", "Free Throw Percentage": ".835", "Win Shares": "214.0", "Win Shares Per 48 Minutes": ".250"}, {"Rank": "2", "Player": "Bill Russell", "From": "1957", "To": "1969", "Games": "963", "Minutes Played Per Game": "42.3", "Points Per Game": "15.1", "Total Rebounds Per Game": "22.5", "Assists Per Game": "4.3", "Steals Per Game": "", "Blocks Per Game": "", "Field Goal Percentage": ".440", "3-Point Field Goal Percentage": "", "Free Throw Percentage": ".561", "Win Shares": "163.5", "Win Shares Per 48 Minutes": ".193"}, {"Rank": "3", "Player": "Kareem Abdul-Jabbar", "From": "1970", "To": "1989", "Games": "1560", "Minutes Played Per Game": "36.8", "Points Per Game": "24.6", "Total Rebounds Per Game": "11.2", "Assists Per Game": "3.6", "Steals Per Game": "0.9", "Blocks Per Game": "2.6", "Field Goal Percentage": ".559", "3-Point Field Goal Percentage": "", "Free Throw Percentage": ".721", "Win Shares": "273.4", "Win Shares Per 48 Minutes": ".228"}, {"Rank": "4", "Player": "Magic Johnson", "From": "1980", "To": "1996", "Games": "906", "Minutes Played Per Game": "36.7", "Points Per Game": "19.5", "Total Rebounds Per Game": "7.2", "Assists Per Game": "11.2", "Steals Per Game": "1.9", "Blocks Per Game": "0.4", "Field Goal Percentage": ".520", "3-Point Field Goal Percentage": ".303", "Free Throw Percentage": ".848", "Win Shares": "155.8", "Win Shares Per 48 Minutes": ".225"}, {"Rank": "5", "Player": "Larry Bird", "From": "1980", "To": "1992", "Games": "897", "Minutes Played Per Game": "38.4", "Points Per Game": "24.3", "Total Rebounds Per Game": "10.0", "Assists Per Game": "6.3", "Steals Per Game": "1.7", "Blocks Per Game": "0.8", "Field Goal Percentage": ".496", "3-Point Field Goal Percentage": ".376", "Free Throw Percentage": ".886", "Win Shares": "145.8", "Win Shares Per 48 Minutes": ".203"}, {"Rank": "6", "Player": "Wilt Chamberlain", "From": "1960", "To": "1973", "Games": "1045", "Minutes Played Per Game": "45.8", "Points Per Game": "30.1", "Total Rebounds Per Game": "22.9", "Assists Per Game": "4.4", "Steals Per Game": "", "Blocks Per Game": "", "Field Goal Percentage": ".540", "3-Point Field Goal Percentage": "", "Free Throw Percentage": ".511", "Win Shares": "247.3", "Win Shares Per 48 Minutes": ".248"}, {"Rank": "7", "Player": "Tim Duncan", "From": "1998", "To": "2016", "Games": "1392", "Minutes Played Per Game": "34.0", "Points Per Game": "19.0", "Total Rebounds Per Game": "10.8", "Assists Per Game": "3.0", "Steals Per Game": "0.7", "Blocks Per Game": "2.2", "Field Goal Percentage": ".506", "3-Point Field Goal Percentage": ".179", "Free Throw Percentage": ".696", "Win Shares": "206.4", "Win Shares Per 48 Minutes": ".209"}, {"Rank": "8", "Player": "Kobe Bryant", "From": "1997", "To": "2016", "Games": "1346", "Minutes Played Per Game": "36.1", "Points Per Game": "25.0", "Total Rebounds Per Game": "5.2", "Assists Per Game": "4.7", "Steals Per Game": "1.4", "Blocks Per Game": "0.5", "Field Goal Percentage": ".447", "3-Point Field Goal Percentage": ".329", "Free Throw Percentage": ".837", "Win Shares": "172.7", "Win Shares Per 48 Minutes": ".170"}, {"Rank": "9", "Player": "Jerry West", "From": "1961", "To": "1974", "Games": "932", "Minutes Played Per Game": "39.2", "Points Per Game": "27.0", "Total Rebounds Per Game": "5.8", "Assists Per Game": "6.7", "Steals Per Game": "2.6", "Blocks Per Game": "0.7", "Field Goal Percentage": ".474", "3-Point Field Goal Percentage": "", "Free Throw Percentage": ".814", "Win Shares": "162.6", "Win Shares Per 48 Minutes": ".213"}, {"Rank": "10", "Player": "Oscar Robertson", "From": "1961", "To": "1974", "Games": "1040", "Minutes Played Per Game": "42.2", "Points Per Game": "25.7", "Total Rebounds Per Game": "7.5", "Assists Per Game": "9.5", "Steals Per Game": "1.1", "Blocks Per Game": "0.1", "Field Goal Percentage": ".485", "3-Point Field Goal Percentage": "", "Free Throw Percentage": ".838", "Win Shares": "189.2", "Win Shares Per 48 Minutes": ".207"}, {"Rank": "11", "Player": "Hakeem Olajuwon", "From": "1985", "To": "2002", "Games": "1238", "Minutes Played Per Game": "35.7", "Points Per Game": "21.8", "Total Rebounds Per Game": "11.1", "Assists Per Game": "2.5", "Steals Per Game": "1.7", "Blocks Per Game": "3.1", "Field Goal Percentage": ".512", "3-Point Field Goal Percentage": ".202", "Free Throw Percentage": ".712", "Win Shares": "162.8", "Win Shares Per 48 Minutes": ".177"}, {"Rank": "12", "Player": "Shaquille O'Neal", "From": "1993", "To": "2011", "Games": "1207", "Minutes Played Per Game": "34.7", "Points Per Game": "23.7", "Total Rebounds Per Game": "10.9", "Assists Per Game": "2.5", "Steals Per Game": "0.6", "Blocks Per Game": "2.3", "Field Goal Percentage": ".582", "3-Point Field Goal Percentage": ".045", "Free Throw Percentage": ".527", "Win Shares": "181.7", "Win Shares Per 48 Minutes": ".208"}, {"Rank": "13", "Player": "Moses Malone", "From": "1977", "To": "1995", "Games": "1329", "Minutes Played Per Game": "33.9", "Points Per Game": "20.6", "Total Rebounds Per Game": "12.2", "Assists Per Game": "1.4", "Steals Per Game": "0.8", "Blocks Per Game": "1.3", "Field Goal Percentage": ".491", "3-Point Field Goal Percentage": "", "Free Throw Percentage": ".769", "Win Shares": "167.1", "Win Shares Per 48 Minutes": ".178"}, {"Rank": "14", "Player": "John Havlicek", "From": "1963", "To": "1978", "Games": "1270", "Minutes Played Per Game": "36.6", "Points Per Game": "20.8", "Total Rebounds Per Game": "6.3", "Assists Per Game": "4.8", "Steals Per Game": "1.2", "Blocks Per Game": "0.3", "Field Goal Percentage": ".439", "3-Point Field Goal Percentage": "", "Free Throw Percentage": ".815", "Win Shares": "131.7", "Win Shares Per 48 Minutes": ".136"}, {"Rank": "15", "Player": "Elgin Baylor", "From": "1959", "To": "1972", "Games": "846", "Minutes Played Per Game": "40.0", "Points Per Game": "27.4", "Total Rebounds Per Game": "13.5", "Assists Per Game": "4.3", "Steals Per Game": "", "Blocks Per Game": "", "Field Goal Percentage": ".431", "3-Point Field Goal Percentage": "", "Free Throw Percentage": ".780", "Win Shares": "104.2", "Win Shares Per 48 Minutes": ".148"}, {"Rank": "16", "Player": "Julius Erving", "From": "1977", "To": "1987", "Games": "836", "Minutes Played Per Game": "34.3", "Points Per Game": "22.0", "Total Rebounds Per Game": "6.7", "Assists Per Game": "3.9", "Steals Per Game": "1.8", "Blocks Per Game": "1.5", "Field Goal Percentage": ".507", "3-Point Field Goal Percentage": "", "Free Throw Percentage": ".777", "Win Shares": "106.2", "Win Shares Per 48 Minutes": ".178"}, {"Rank": "17", "Player": "Bob Pettit", "From": "1955", "To": "1965", "Games": "792", "Minutes Played Per Game": "38.8", "Points Per Game": "26.4", "Total Rebounds Per Game": "16.2", "Assists Per Game": "3.0", "Steals Per Game": "", "Blocks Per Game": "", "Field Goal Percentage": ".436", "3-Point Field Goal Percentage": "", "Free Throw Percentage": ".761", "Win Shares": "136.0", "Win Shares Per 48 Minutes": ".213"}, {"Rank": "18", "Player": "Karl Malone", "From": "1986", "To": "2004", "Games": "1476", "Minutes Played Per Game": "37.2", "Points Per Game": "25.0", "Total Rebounds Per Game": "10.1", "Assists Per Game": "3.6", "Steals Per Game": "1.4", "Blocks Per Game": "0.8", "Field Goal Percentage": ".516", "3-Point Field Goal Percentage": ".274", "Free Throw Percentage": ".742", "Win Shares": "234.6", "Win Shares Per 48 Minutes": ".205"}, {"Rank": "19", "Player": "Charles Barkley", "From": "1985", "To": "2000", "Games": "1073", "Minutes Played Per Game": "36.7", "Points Per Game": "22.1", "Total Rebounds Per Game": "11.7", "Assists Per Game": "3.9", "Steals Per Game": "1.5", "Blocks Per Game": "0.8", "Field Goal Percentage": ".541", "3-Point Field Goal Percentage": ".266", "Free Throw Percentage": ".735", "Win Shares": "177.2", "Win Shares Per 48 Minutes": ".216"}, {"Rank": "20", "Player": "LeBron James", "From": "2004", "To": "2023", "Games": "1421", "Minutes Played Per Game": "38.1", "Points Per Game": "27.2", "Total Rebounds Per Game": "7.5", "Assists Per Game": "7.3", "Steals Per Game": "1.5", "Blocks Per Game": "0.8", "Field Goal Percentage": ".505", "3-Point Field Goal Percentage": ".345", "Free Throw Percentage": ".735", "Win Shares": "255.1", "Win Shares Per 48 Minutes": ".226"}, {"Rank": "21", "Player": "Bob Cousy", "From": "1951", "To": "1970", "Games": "924", "Minutes Played Per Game": "35.3", "Points Per Game": "18.4", "Total Rebounds Per Game": "5.2", "Assists Per Game": "7.5", "Steals Per Game": "", "Blocks Per Game": "", "Field Goal Percentage": ".375", "3-Point Field Goal Percentage": "", "Free Throw Percentage": ".803", "Win Shares": "91.1", "Win Shares Per 48 Minutes": ".139"}, {"Rank": "22", "Player": "Kevin Garnett", "From": "1996", "To": "2016", "Games": "1462", "Minutes Played Per Game": "34.5", "Points Per Game": "17.8", "Total Rebounds Per Game": "10.0", "Assists Per Game": "3.7", "Steals Per Game": "1.3", "Blocks Per Game": "1.4", "Field Goal Percentage": ".497", "3-Point Field Goal Percentage": ".275", "Free Throw Percentage": ".789", "Win Shares": "191.4", "Win Shares Per 48 Minutes": ".182"}, {"Rank": "23", "Player": "Isiah Thomas", "From": "1982", "To": "1994", "Games": "979", "Minutes Played Per Game": "36.3", "Points Per Game": "19.2", "Total Rebounds Per Game": "3.6", "Assists Per Game": "9.3", "Steals Per Game": "1.9", "Blocks Per Game": "0.3", "Field Goal Percentage": ".452", "3-Point Field Goal Percentage": ".290", "Free Throw Percentage": ".759", "Win Shares": "80.7", "Win Shares Per 48 Minutes": ".109"}, {"Rank": "24", "Player": "Scottie Pippen", "From": "1988", "To": "2004", "Games": "1178", "Minutes Played Per Game": "34.9", "Points Per Game": "16.1", "Total Rebounds Per Game": "6.4", "Assists Per Game": "5.2", "Steals Per Game": "2.0", "Blocks Per Game": "0.8", "Field Goal Percentage": ".473", "3-Point Field Goal Percentage": ".326", "Free Throw Percentage": ".704", "Win Shares": "125.1", "Win Shares Per 48 Minutes": ".146"}, {"Rank": "25", "Player": "John Stockton", "From": "1985", "To": "2003", "Games": "1504", "Minutes Played Per Game": "31.8", "Points Per Game": "13.1", "Total Rebounds Per Game": "2.7", "Assists Per Game": "10.5", "Steals Per Game": "2.2", "Blocks Per Game": "0.2", "Field Goal Percentage": ".515", "3-Point Field Goal Percentage": ".384", "Free Throw Percentage": ".826", "Win Shares": "207.7", "Win Shares Per 48 Minutes": ".209"}, {"Rank": "26", "Player": "Rick Barry", "From": "1966", "To": "1980", "Games": "794", "Minutes Played Per Game": "36.3", "Points Per Game": "23.2", "Total Rebounds Per Game": "6.5", "Assists Per Game": "5.1", "Steals Per Game": "2.0", "Blocks Per Game": "0.5", "Field Goal Percentage": ".449", "3-Point Field Goal Percentage": "", "Free Throw Percentage": ".900", "Win Shares": "93.4", "Win Shares Per 48 Minutes": ".156"}, {"Rank": "27", "Player": "Bill Walton", "From": "1975", "To": "1987", "Games": "468", "Minutes Played Per Game": "28.3", "Points Per Game": "13.3", "Total Rebounds Per Game": "10.5", "Assists Per Game": "3.4", "Steals Per Game": "0.8", "Blocks Per Game": "2.2", "Field Goal Percentage": ".521", "3-Point Field Goal Percentage": "", "Free Throw Percentage": ".660", "Win Shares": "39.3", "Win Shares Per 48 Minutes": ".142"}, {"Rank": "28", "Player": "Dwyane Wade", "From": "2004", "To": "2019", "Games": "1054", "Minutes Played Per Game": "33.9", "Points Per Game": "22.0", "Total Rebounds Per Game": "4.7", "Assists Per Game": "5.4", "Steals Per Game": "1.5", "Blocks Per Game": "0.8", "Field Goal Percentage": ".480", "3-Point Field Goal Percentage": ".293", "Free Throw Percentage": ".765", "Win Shares": "120.7", "Win Shares Per 48 Minutes": ".162"}, {"Rank": "29", "Player": "David Robinson", "From": "1990", "To": "2003", "Games": "987", "Minutes Played Per Game": "34.7", "Points Per Game": "21.1", "Total Rebounds Per Game": "10.6", "Assists Per Game": "2.5", "Steals Per Game": "1.4", "Blocks Per Game": "3.0", "Field Goal Percentage": ".518", "3-Point Field Goal Percentage": ".250", "Free Throw Percentage": ".736", "Win Shares": "178.7", "Win Shares Per 48 Minutes": ".250"}, {"Rank": "30", "Player": "Willis Reed", "From": "1965", "To": "1974", "Games": "650", "Minutes Played Per Game": "35.5", "Points Per Game": "18.7", "Total Rebounds Per Game": "12.9", "Assists Per Game": "1.8", "Steals Per Game": "0.6", "Blocks Per Game": "1.1", "Field Goal Percentage": ".476", "3-Point Field Goal Percentage": "", "Free Throw Percentage": ".747", "Win Shares": "74.9", "Win Shares Per 48 Minutes": ".156"}, {"Rank": "31", "Player": "Dave Cowens", "From": "1971", "To": "1983", "Games": "766", "Minutes Played Per Game": "38.6", "Points Per Game": "17.6", "Total Rebounds Per Game": "13.6", "Assists Per Game": "3.8", "Steals Per Game": "1.1", "Blocks Per Game": "0.9", "Field Goal Percentage": ".460", "3-Point Field Goal Percentage": "", "Free Throw Percentage": ".783", "Win Shares": "86.3", "Win Shares Per 48 Minutes": ".140"}, {"Rank": "32", "Player": "Walt Frazier", "From": "1968", "To": "1980", "Games": "825", "Minutes Played Per Game": "37.5", "Points Per Game": "18.9", "Total Rebounds Per Game": "5.9", "Assists Per Game": "6.1", "Steals Per Game": "1.9", "Blocks Per Game": "0.2", "Field Goal Percentage": ".490", "3-Point Field Goal Percentage": "", "Free Throw Percentage": ".786", "Win Shares": "113.5", "Win Shares Per 48 Minutes": ".176"}, {"Rank": "33", "Player": "Sam Jones", "From": "1958", "To": "1969", "Games": "871", "Minutes Played Per Game": "27.9", "Points Per Game": "17.7", "Total Rebounds Per Game": "4.9", "Assists Per Game": "2.5", "Steals Per Game": "", "Blocks Per Game": "", "Field Goal Percentage": ".456", "3-Point Field Goal Percentage": "", "Free Throw Percentage": ".803", "Win Shares": "92.3", "Win Shares Per 48 Minutes": ".182"}, {"Rank": "34", "Player": "George Gervin", "From": "1977", "To": "1986", "Games": "791", "Minutes Played Per Game": "33.5", "Points Per Game": "26.2", "Total Rebounds Per Game": "4.6", "Assists Per Game": "2.8", "Steals Per Game": "1.2", "Blocks Per Game": "0.8", "Field Goal Percentage": ".511", "3-Point Field Goal Percentage": "", "Free Throw Percentage": ".844", "Win Shares": "88.1", "Win Shares Per 48 Minutes": ".159"}, {"Rank": "35", "Player": "Kevin McHale", "From": "1981", "To": "1993", "Games": "971", "Minutes Played Per Game": "31.0", "Points Per Game": "17.9", "Total Rebounds Per Game": "7.3", "Assists Per Game": "1.7", "Steals Per Game": "0.4", "Blocks Per Game": "1.7", "Field Goal Percentage": ".554", "3-Point Field Goal Percentage": ".261", "Free Throw Percentage": ".798", "Win Shares": "113.0", "Win Shares Per 48 Minutes": ".180"}, {"Rank": "36", "Player": "Steve Nash", "From": "1997", "To": "2014", "Games": "1217", "Minutes Played Per Game": "31.3", "Points Per Game": "14.3", "Total Rebounds Per Game": "3.0", "Assists Per Game": "8.5", "Steals Per Game": "0.7", "Blocks Per Game": "0.1", "Field Goal Percentage": ".490", "3-Point Field Goal Percentage": ".428", "Free Throw Percentage": ".904", "Win Shares": "129.7", "Win Shares Per 48 Minutes": ".164"}, {"Rank": "37", "Player": "Allen Iverson", "From": "1997", "To": "2010", "Games": "914", "Minutes Played Per Game": "41.1", "Points Per Game": "26.7", "Total Rebounds Per Game": "3.7", "Assists Per Game": "6.2", "Steals Per Game": "2.2", "Blocks Per Game": "0.2", "Field Goal Percentage": ".425", "3-Point Field Goal Percentage": ".313", "Free Throw Percentage": ".780", "Win Shares": "99.0", "Win Shares Per 48 Minutes": ".126"}, {"Rank": "38", "Player": "George Mikan", "From": "1949", "To": "1956", "Games": "439", "Minutes Played Per Game": "34.4", "Points Per Game": "23.1", "Total Rebounds Per Game": "13.4", "Assists Per Game": "2.8", "Steals Per Game": "", "Blocks Per Game": "", "Field Goal Percentage": ".404", "3-Point Field Goal Percentage": "", "Free Throw Percentage": ".782", "Win Shares": "108.7", "Win Shares Per 48 Minutes": ".249"}, {"Rank": "39", "Player": "Dirk Nowitzki", "From": "1999", "To": "2019", "Games": "1522", "Minutes Played Per Game": "33.8", "Points Per Game": "20.7", "Total Rebounds Per Game": "7.5", "Assists Per Game": "2.4", "Steals Per Game": "0.8", "Blocks Per Game": "0.8", "Field Goal Percentage": ".471", "3-Point Field Goal Percentage": ".380", "Free Throw Percentage": ".879", "Win Shares": "206.3", "Win Shares Per 48 Minutes": ".193"}, {"Rank": "40", "Player": "Patrick Ewing", "From": "1986", "To": "2002", "Games": "1183", "Minutes Played Per Game": "34.3", "Points Per Game": "21.0", "Total Rebounds Per Game": "9.8", "Assists Per Game": "1.9", "Steals Per Game": "1.0", "Blocks Per Game": "2.4", "Field Goal Percentage": ".504", "3-Point Field Goal Percentage": ".152", "Free Throw Percentage": ".740", "Win Shares": "126.4", "Win Shares Per 48 Minutes": ".150"}, {"Rank": "41", "Player": "Gary Payton", "From": "1991", "To": "2007", "Games": "1335", "Minutes Played Per Game": "35.3", "Points Per Game": "16.3", "Total Rebounds Per Game": "3.9", "Assists Per Game": "6.7", "Steals Per Game": "1.8", "Blocks Per Game": "0.2", "Field Goal Percentage": ".466", "3-Point Field Goal Percentage": ".317", "Free Throw Percentage": ".729", "Win Shares": "145.5", "Win Shares Per 48 Minutes": ".148"}, {"Rank": "42", "Player": "Wes Unseld", "From": "1969", "To": "1981", "Games": "984", "Minutes Played Per Game": "36.4", "Points Per Game": "10.8", "Total Rebounds Per Game": "14.0", "Assists Per Game": "3.9", "Steals Per Game": "1.1", "Blocks Per Game": "0.6", "Field Goal Percentage": ".509", "3-Point Field Goal Percentage": "", "Free Throw Percentage": ".633", "Win Shares": "110.1", "Win Shares Per 48 Minutes": ".147"}, {"Rank": "43", "Player": "Jason Kidd", "From": "1995", "To": "2013", "Games": "1391", "Minutes Played Per Game": "36.0", "Points Per Game": "12.6", "Total Rebounds Per Game": "6.3", "Assists Per Game": "8.7", "Steals Per Game": "1.9", "Blocks Per Game": "0.3", "Field Goal Percentage": ".400", "3-Point Field Goal Percentage": ".349", "Free Throw Percentage": ".785", "Win Shares": "138.6", "Win Shares Per 48 Minutes": ".133"}, {"Rank": "44", "Player": "Clyde Drexler", "From": "1984", "To": "1998", "Games": "1086", "Minutes Played Per Game": "34.6", "Points Per Game": "20.4", "Total Rebounds Per Game": "6.1", "Assists Per Game": "5.6", "Steals Per Game": "2.0", "Blocks Per Game": "0.7", "Field Goal Percentage": ".472", "3-Point Field Goal Percentage": ".318", "Free Throw Percentage": ".788", "Win Shares": "135.6", "Win Shares Per 48 Minutes": ".173"}, {"Rank": "45", "Player": "Nate Thurmond", "From": "1964", "To": "1977", "Games": "964", "Minutes Played Per Game": "37.2", "Points Per Game": "15.0", "Total Rebounds Per Game": "15.0", "Assists Per Game": "2.7", "Steals Per Game": "0.5", "Blocks Per Game": "2.1", "Field Goal Percentage": ".421", "3-Point Field Goal Percentage": "", "Free Throw Percentage": ".667", "Win Shares": "78.0", "Win Shares Per 48 Minutes": ".104"}, {"Rank": "46", "Player": "Dave DeBusschere", "From": "1963", "To": "1974", "Games": "875", "Minutes Played Per Game": "35.7", "Points Per Game": "16.1", "Total Rebounds Per Game": "11.0", "Assists Per Game": "2.9", "Steals Per Game": "0.9", "Blocks Per Game": "0.5", "Field Goal Percentage": ".432", "3-Point Field Goal Percentage": "", "Free Throw Percentage": ".699", "Win Shares": "60.8", "Win Shares Per 48 Minutes": ".093"}, {"Rank": "47", "Player": "Paul Pierce", "From": "1999", "To": "2017", "Games": "1343", "Minutes Played Per Game": "34.2", "Points Per Game": "19.7", "Total Rebounds Per Game": "5.6", "Assists Per Game": "3.5", "Steals Per Game": "1.3", "Blocks Per Game": "0.6", "Field Goal Percentage": ".445", "3-Point Field Goal Percentage": ".368", "Free Throw Percentage": ".806", "Win Shares": "150.0", "Win Shares Per 48 Minutes": ".157"}, {"Rank": "48", "Player": "Hal Greer", "From": "1959", "To": "1973", "Games": "1122", "Minutes Played Per Game": "35.5", "Points Per Game": "19.2", "Total Rebounds Per Game": "5.0", "Assists Per Game": "4.0", "Steals Per Game": "", "Blocks Per Game": "", "Field Goal Percentage": ".452", "3-Point Field Goal Percentage": "", "Free Throw Percentage": ".801", "Win Shares": "102.7", "Win Shares Per 48 Minutes": ".124"}, {"Rank": "49", "Player": "Billy Cunningham", "From": "1966", "To": "1976", "Games": "654", "Minutes Played Per Game": "34.3", "Points Per Game": "20.8", "Total Rebounds Per Game": "10.1", "Assists Per Game": "4.0", "Steals Per Game": "1.2", "Blocks Per Game": "0.5", "Field Goal Percentage": ".446", "3-Point Field Goal Percentage": "", "Free Throw Percentage": ".720", "Win Shares": "63.2", "Win Shares Per 48 Minutes": ".135"}, {"Rank": "50", "Player": "James Worthy", "From": "1983", "To": "1994", "Games": "926", "Minutes Played Per Game": "32.4", "Points Per Game": "17.6", "Total Rebounds Per Game": "5.1", "Assists Per Game": "3.0", "Steals Per Game": "1.1", "Blocks Per Game": "0.7", "Field Goal Percentage": ".521", "3-Point Field Goal Percentage": ".241", "Free Throw Percentage": ".769", "Win Shares": "81.2", "Win Shares Per 48 Minutes": ".130"}, {"Rank": "51", "Player": "Elvin Hayes", "From": "1969", "To": "1984", "Games": "1303", "Minutes Played Per Game": "38.4", "Points Per Game": "21.0", "Total Rebounds Per Game": "12.5", "Assists Per Game": "1.8", "Steals Per Game": "1.0", "Blocks Per Game": "2.0", "Field Goal Percentage": ".452", "3-Point Field Goal Percentage": "", "Free Throw Percentage": ".670", "Win Shares": "120.8", "Win Shares Per 48 Minutes": ".116"}, {"Rank": "52", "Player": "Dolph Schayes", "From": "1950", "To": "1964", "Games": "996", "Minutes Played Per Game": "34.4", "Points Per Game": "18.5", "Total Rebounds Per Game": "12.1", "Assists Per Game": "3.1", "Steals Per Game": "", "Blocks Per Game": "", "Field Goal Percentage": ".380", "3-Point Field Goal Percentage": "", "Free Throw Percentage": ".849", "Win Shares": "142.4", "Win Shares Per 48 Minutes": ".192"}, {"Rank": "53", "Player": "Bill Sharman", "From": "1951", "To": "1961", "Games": "711", "Minutes Played Per Game": "32.0", "Points Per Game": "17.8", "Total Rebounds Per Game": "3.9", "Assists Per Game": "3.0", "Steals Per Game": "", "Blocks Per Game": "", "Field Goal Percentage": ".426", "3-Point Field Goal Percentage": "", "Free Throw Percentage": ".883", "Win Shares": "82.8", "Win Shares Per 48 Minutes": ".178"}, {"Rank": "54", "Player": "Dennis Johnson", "From": "1977", "To": "1990", "Games": "1100", "Minutes Played Per Game": "32.7", "Points Per Game": "14.1", "Total Rebounds Per Game": "3.9", "Assists Per Game": "5.0", "Steals Per Game": "1.3", "Blocks Per Game": "0.6", "Field Goal Percentage": ".445", "3-Point Field Goal Percentage": "", "Free Throw Percentage": ".797", "Win Shares": "82.6", "Win Shares Per 48 Minutes": ".110"}, {"Rank": "55", "Player": "Dominique Wilkins", "From": "1983", "To": "1999", "Games": "1074", "Minutes Played Per Game": "35.5", "Points Per Game": "24.8", "Total Rebounds Per Game": "6.7", "Assists Per Game": "2.5", "Steals Per Game": "1.3", "Blocks Per Game": "0.6", "Field Goal Percentage": ".461", "3-Point Field Goal Percentage": ".319", "Free Throw Percentage": ".811", "Win Shares": "117.5", "Win Shares Per 48 Minutes": ".148"}, {"Rank": "56", "Player": "Paul Arizin", "From": "1951", "To": "1962", "Games": "713", "Minutes Played Per Game": "38.4", "Points Per Game": "22.8", "Total Rebounds Per Game": "8.6", "Assists Per Game": "2.3", "Steals Per Game": "", "Blocks Per Game": "", "Field Goal Percentage": ".421", "3-Point Field Goal Percentage": "", "Free Throw Percentage": ".810", "Win Shares": "108.8", "Win Shares Per 48 Minutes": ".183"}, {"Rank": "57", "Player": "Tom Heinsohn", "From": "1957", "To": "1965", "Games": "654", "Minutes Played Per Game": "29.4", "Points Per Game": "18.6", "Total Rebounds Per Game": "8.8", "Assists Per Game": "2.0", "Steals Per Game": "", "Blocks Per Game": "", "Field Goal Percentage": ".405", "3-Point Field Goal Percentage": "", "Free Throw Percentage": ".790", "Win Shares": "60.0", "Win Shares Per 48 Minutes": ".150"}, {"Rank": "58", "Player": "Bernard King", "From": "1978", "To": "1993", "Games": "874", "Minutes Played Per Game": "33.7", "Points Per Game": "22.5", "Total Rebounds Per Game": "5.8", "Assists Per Game": "3.3", "Steals Per Game": "1.0", "Blocks Per Game": "0.3", "Field Goal Percentage": ".518", "3-Point Field Goal Percentage": "", "Free Throw Percentage": ".730", "Win Shares": "75.4", "Win Shares Per 48 Minutes": ".123"}, {"Rank": "59", "Player": "Robert Parish", "From": "1977", "To": "1997", "Games": "1611", "Minutes Played Per Game": "28.4", "Points Per Game": "14.5", "Total Rebounds Per Game": "9.1", "Assists Per Game": "1.4", "Steals Per Game": "0.8", "Blocks Per Game": "1.5", "Field Goal Percentage": ".537", "3-Point Field Goal Percentage": "", "Free Throw Percentage": ".721", "Win Shares": "147.0", "Win Shares Per 48 Minutes": ".154"}, {"Rank": "60", "Player": "Tiny Archibald", "From": "1971", "To": "1984", "Games": "876", "Minutes Played Per Game": "35.6", "Points Per Game": "18.8", "Total Rebounds Per Game": "2.3", "Assists Per Game": "7.4", "Steals Per Game": "1.1", "Blocks Per Game": "0.1", "Field Goal Percentage": ".467", "3-Point Field Goal Percentage": "", "Free Throw Percentage": ".810", "Win Shares": "83.4", "Win Shares Per 48 Minutes": ".128"}, {"Rank": "61", "Player": "Bob McAdoo", "From": "1973", "To": "1986", "Games": "852", "Minutes Played Per Game": "33.2", "Points Per Game": "22.1", "Total Rebounds Per Game": "9.4", "Assists Per Game": "2.3", "Steals Per Game": "1.0", "Blocks Per Game": "1.5", "Field Goal Percentage": ".503", "3-Point Field Goal Percentage": "", "Free Throw Percentage": ".754", "Win Shares": "89.1", "Win Shares Per 48 Minutes": ".151"}, {"Rank": "62", "Player": "Ray Allen", "From": "1997", "To": "2014", "Games": "1300", "Minutes Played Per Game": "35.6", "Points Per Game": "18.9", "Total Rebounds Per Game": "4.1", "Assists Per Game": "3.4", "Steals Per Game": "1.1", "Blocks Per Game": "0.2", "Field Goal Percentage": ".452", "3-Point Field Goal Percentage": ".400", "Free Throw Percentage": ".894", "Win Shares": "145.1", "Win Shares Per 48 Minutes": ".150"}, {"Rank": "63", "Player": "Reggie Miller", "From": "1988", "To": "2005", "Games": "1389", "Minutes Played Per Game": "34.3", "Points Per Game": "18.2", "Total Rebounds Per Game": "3.0", "Assists Per Game": "3.0", "Steals Per Game": "1.1", "Blocks Per Game": "0.2", "Field Goal Percentage": ".471", "3-Point Field Goal Percentage": ".395", "Free Throw Percentage": ".888", "Win Shares": "174.4", "Win Shares Per 48 Minutes": ".176"}, {"Rank": "64", "Player": "Jerry Lucas", "From": "1964", "To": "1974", "Games": "829", "Minutes Played Per Game": "38.8", "Points Per Game": "17.0", "Total Rebounds Per Game": "15.6", "Assists Per Game": "3.3", "Steals Per Game": "0.4", "Blocks Per Game": "0.3", "Field Goal Percentage": ".499", "3-Point Field Goal Percentage": "", "Free Throw Percentage": ".783", "Win Shares": "98.4", "Win Shares Per 48 Minutes": ".147"}, {"Rank": "65", "Player": "Alex English", "From": "1977", "To": "1991", "Games": "1193", "Minutes Played Per Game": "31.9", "Points Per Game": "21.5", "Total Rebounds Per Game": "5.5", "Assists Per Game": "3.6", "Steals Per Game": "0.9", "Blocks Per Game": "0.7", "Field Goal Percentage": ".507", "3-Point Field Goal Percentage": "", "Free Throw Percentage": ".832", "Win Shares": "100.7", "Win Shares Per 48 Minutes": ".127"}, {"Rank": "66", "Player": "Adrian Dantley", "From": "1977", "To": "1991", "Games": "955", "Minutes Played Per Game": "35.8", "Points Per Game": "24.3", "Total Rebounds Per Game": "5.7", "Assists Per Game": "3.0", "Steals Per Game": "1.0", "Blocks Per Game": "0.2", "Field Goal Percentage": ".540", "3-Point Field Goal Percentage": "", "Free Throw Percentage": ".818", "Win Shares": "134.2", "Win Shares Per 48 Minutes": ".189"}, {"Rank": "67", "Player": "Earl Monroe", "From": "1968", "To": "1980", "Games": "926", "Minutes Played Per Game": "32.0", "Points Per Game": "18.8", "Total Rebounds Per Game": "3.0", "Assists Per Game": "3.9", "Steals Per Game": "1.0", "Blocks Per Game": "0.3", "Field Goal Percentage": ".464", "3-Point Field Goal Percentage": "", "Free Throw Percentage": ".807", "Win Shares": "77.4", "Win Shares Per 48 Minutes": ".125"}, {"Rank": "68", "Player": "Pete Maravich", "From": "1971", "To": "1980", "Games": "658", "Minutes Played Per Game": "37.0", "Points Per Game": "24.2", "Total Rebounds Per Game": "4.2", "Assists Per Game": "5.4", "Steals Per Game": "1.4", "Blocks Per Game": "0.3", "Field Goal Percentage": ".441", "3-Point Field Goal Percentage": "", "Free Throw Percentage": ".820", "Win Shares": "46.7", "Win Shares Per 48 Minutes": ".092"}, {"Rank": "69", "Player": "Dennis Rodman", "From": "1987", "To": "2000", "Games": "911", "Minutes Played Per Game": "31.7", "Points Per Game": "7.3", "Total Rebounds Per Game": "13.1", "Assists Per Game": "1.8", "Steals Per Game": "0.7", "Blocks Per Game": "0.6", "Field Goal Percentage": ".521", "3-Point Field Goal Percentage": ".231", "Free Throw Percentage": ".584", "Win Shares": "89.8", "Win Shares Per 48 Minutes": ".150"}, {"Rank": "70", "Player": "David Thompson", "From": "1977", "To": "1984", "Games": "509", "Minutes Played Per Game": "32.0", "Points Per Game": "22.1", "Total Rebounds Per Game": "3.8", "Assists Per Game": "3.2", "Steals Per Game": "0.9", "Blocks Per Game": "0.8", "Field Goal Percentage": ".504", "3-Point Field Goal Percentage": "", "Free Throw Percentage": ".778", "Win Shares": "50.8", "Win Shares Per 48 Minutes": ".150"}, {"Rank": "71", "Player": "Lenny Wilkens", "From": "1961", "To": "1975", "Games": "1077", "Minutes Played Per Game": "35.3", "Points Per Game": "16.5", "Total Rebounds Per Game": "4.7", "Assists Per Game": "6.7", "Steals Per Game": "1.3", "Blocks Per Game": "0.2", "Field Goal Percentage": ".432", "3-Point Field Goal Percentage": "", "Free Throw Percentage": ".774", "Win Shares": "95.5", "Win Shares Per 48 Minutes": ".120"}, {"Rank": "72", "Player": "Chris Webber", "From": "1994", "To": "2008", "Games": "831", "Minutes Played Per Game": "37.1", "Points Per Game": "20.7", "Total Rebounds Per Game": "9.8", "Assists Per Game": "4.2", "Steals Per Game": "1.4", "Blocks Per Game": "1.4", "Field Goal Percentage": ".479", "3-Point Field Goal Percentage": ".299", "Free Throw Percentage": ".649", "Win Shares": "84.7", "Win Shares Per 48 Minutes": ".132"}, {"Rank": "73", "Player": "Sidney Moncrief", "From": "1980", "To": "1991", "Games": "767", "Minutes Played Per Game": "30.2", "Points Per Game": "15.6", "Total Rebounds Per Game": "4.7", "Assists Per Game": "3.6", "Steals Per Game": "1.2", "Blocks Per Game": "0.3", "Field Goal Percentage": ".502", "3-Point Field Goal Percentage": ".284", "Free Throw Percentage": ".831", "Win Shares": "90.3", "Win Shares Per 48 Minutes": ".187"}, {"Rank": "74", "Player": "Joe Dumars", "From": "1986", "To": "1999", "Games": "1018", "Minutes Played Per Game": "34.5", "Points Per Game": "16.1", "Total Rebounds Per Game": "2.2", "Assists Per Game": "4.5", "Steals Per Game": "0.9", "Blocks Per Game": "0.1", "Field Goal Percentage": ".460", "3-Point Field Goal Percentage": ".382", "Free Throw Percentage": ".843", "Win Shares": "86.2", "Win Shares Per 48 Minutes": ".118"}, {"Rank": "75", "Player": "Artis Gilmore", "From": "1977", "To": "1988", "Games": "909", "Minutes Played Per Game": "32.7", "Points Per Game": "17.1", "Total Rebounds Per Game": "10.1", "Assists Per Game": "2.0", "Steals Per Game": "0.5", "Blocks Per Game": "1.9", "Field Goal Percentage": ".599", "3-Point Field Goal Percentage": "", "Free Throw Percentage": ".713", "Win Shares": "107.4", "Win Shares Per 48 Minutes": ".174"}, {"Rank": "76", "Player": "Dan Issel", "From": "1977", "To": "1985", "Games": "718", "Minutes Played Per Game": "31.1", "Points Per Game": "20.4", "Total Rebounds Per Game": "7.9", "Assists Per Game": "2.5", "Steals Per Game": "1.0", "Blocks Per Game": "0.6", "Field Goal Percentage": ".506", "3-Point Field Goal Percentage": "", "Free Throw Percentage": ".797", "Win Shares": "82.3", "Win Shares Per 48 Minutes": ".177"}, {"Rank": "77", "Player": "Tracy McGrady", "From": "1998", "To": "2012", "Games": "938", "Minutes Played Per Game": "32.7", "Points Per Game": "19.6", "Total Rebounds Per Game": "5.6", "Assists Per Game": "4.4", "Steals Per Game": "1.2", "Blocks Per Game": "0.9", "Field Goal Percentage": ".435", "3-Point Field Goal Percentage": ".338", "Free Throw Percentage": ".746", "Win Shares": "97.3", "Win Shares Per 48 Minutes": ".152"}, {"Rank": "78", "Player": "Dwight Howard", "From": "2005", "To": "2022", "Games": "1242", "Minutes Played Per Game": "31.8", "Points Per Game": "15.7", "Total Rebounds Per Game": "11.8", "Assists Per Game": "1.3", "Steals Per Game": "0.9", "Blocks Per Game": "1.8", "Field Goal Percentage": ".587", "3-Point Field Goal Percentage": ".214", "Free Throw Percentage": ".567", "Win Shares": "141.7", "Win Shares Per 48 Minutes": ".172"}, {"Rank": "79", "Player": "Paul Westphal", "From": "1973", "To": "1984", "Games": "823", "Minutes Played Per Game": "25.5", "Points Per Game": "15.6", "Total Rebounds Per Game": "1.9", "Assists Per Game": "4.4", "Steals Per Game": "1.3", "Blocks Per Game": "0.3", "Field Goal Percentage": ".504", "3-Point Field Goal Percentage": "", "Free Throw Percentage": ".820", "Win Shares": "67.7", "Win Shares Per 48 Minutes": ".155"}, {"Rank": "80", "Player": "Bob Dandridge", "From": "1970", "To": "1982", "Games": "839", "Minutes Played Per Game": "35.2", "Points Per Game": "18.5", "Total Rebounds Per Game": "6.8", "Assists Per Game": "3.4", "Steals Per Game": "1.3", "Blocks Per Game": "0.6", "Field Goal Percentage": ".484", "3-Point Field Goal Percentage": "", "Free Throw Percentage": ".780", "Win Shares": "80.3", "Win Shares Per 48 Minutes": ".131"}, {"Rank": "81", "Player": "Dave Bing", "From": "1967", "To": "1978", "Games": "901", "Minutes Played Per Game": "36.4", "Points Per Game": "20.3", "Total Rebounds Per Game": "3.8", "Assists Per Game": "6.0", "Steals Per Game": "1.3", "Blocks Per Game": "0.2", "Field Goal Percentage": ".441", "3-Point Field Goal Percentage": "", "Free Throw Percentage": ".775", "Win Shares": "68.8", "Win Shares Per 48 Minutes": ".101"}, {"Rank": "82", "Player": "Chris Mullin", "From": "1986", "To": "2001", "Games": "986", "Minutes Played Per Game": "32.6", "Points Per Game": "18.2", "Total Rebounds Per Game": "4.1", "Assists Per Game": "3.5", "Steals Per Game": "1.6", "Blocks Per Game": "0.6", "Field Goal Percentage": ".509", "3-Point Field Goal Percentage": ".384", "Free Throw Percentage": ".865", "Win Shares": "93.1", "Win Shares Per 48 Minutes": ".139"}, {"Rank": "83", "Player": "Cliff Hagan", "From": "1957", "To": "1966", "Games": "745", "Minutes Played Per Game": "29.2", "Points Per Game": "18.0", "Total Rebounds Per Game": "6.9", "Assists Per Game": "3.0", "Steals Per Game": "", "Blocks Per Game": "", "Field Goal Percentage": ".450", "3-Point Field Goal Percentage": "", "Free Throw Percentage": ".798", "Win Shares": "75.1", "Win Shares Per 48 Minutes": ".166"}, {"Rank": "84", "Player": "Robert Horry", "From": "1993", "To": "2008", "Games": "1107", "Minutes Played Per Game": "24.5", "Points Per Game": "7.0", "Total Rebounds Per Game": "4.8", "Assists Per Game": "2.1", "Steals Per Game": "1.0", "Blocks Per Game": "0.9", "Field Goal Percentage": ".425", "3-Point Field Goal Percentage": ".341", "Free Throw Percentage": ".726", "Win Shares": "66.3", "Win Shares Per 48 Minutes": ".118"}, {"Rank": "85", "Player": "Arvydas Sabonis", "From": "1996", "To": "2003", "Games": "470", "Minutes Played Per Game": "24.2", "Points Per Game": "12.0", "Total Rebounds Per Game": "7.3", "Assists Per Game": "2.1", "Steals Per Game": "0.8", "Blocks Per Game": "1.1", "Field Goal Percentage": ".500", "3-Point Field Goal Percentage": ".328", "Free Throw Percentage": ".786", "Win Shares": "47.3", "Win Shares Per 48 Minutes": ".200"}, {"Rank": "86", "Player": "Connie Hawkins", "From": "1970", "To": "1976", "Games": "499", "Minutes Played Per Game": "34.5", "Points Per Game": "16.5", "Total Rebounds Per Game": "8.0", "Assists Per Game": "4.1", "Steals Per Game": "1.2", "Blocks Per Game": "0.8", "Field Goal Percentage": ".467", "3-Point Field Goal Percentage": "", "Free Throw Percentage": ".785", "Win Shares": "47.5", "Win Shares Per 48 Minutes": ".132"}, {"Rank": "87", "Player": "Gail Goodrich", "From": "1966", "To": "1979", "Games": "1031", "Minutes Played Per Game": "32.5", "Points Per Game": "18.6", "Total Rebounds Per Game": "3.2", "Assists Per Game": "4.7", "Steals Per Game": "1.3", "Blocks Per Game": "0.2", "Field Goal Percentage": ".456", "3-Point Field Goal Percentage": "", "Free Throw Percentage": ".807", "Win Shares": "76.3", "Win Shares Per 48 Minutes": ".109"}, {"Rank": "88", "Player": "Shawn Kemp", "From": "1990", "To": "2003", "Games": "1051", "Minutes Played Per Game": "27.9", "Points Per Game": "14.6", "Total Rebounds Per Game": "8.4", "Assists Per Game": "1.6", "Steals Per Game": "1.1", "Blocks Per Game": "1.2", "Field Goal Percentage": ".488", "3-Point Field Goal Percentage": ".277", "Free Throw Percentage": ".741", "Win Shares": "89.5", "Win Shares Per 48 Minutes": ".147"}, {"Rank": "89", "Player": "Vince Carter", "From": "1999", "To": "2020", "Games": "1541", "Minutes Played Per Game": "30.1", "Points Per Game": "16.7", "Total Rebounds Per Game": "4.3", "Assists Per Game": "3.1", "Steals Per Game": "1.0", "Blocks Per Game": "0.6", "Field Goal Percentage": ".435", "3-Point Field Goal Percentage": ".371", "Free Throw Percentage": ".798", "Win Shares": "125.3", "Win Shares Per 48 Minutes": ".130"}, {"Rank": "90", "Player": "Chris Paul", "From": "2006", "To": "2023", "Games": "1214", "Minutes Played Per Game": "34.4", "Points Per Game": "17.9", "Total Rebounds Per Game": "4.5", "Assists Per Game": "9.5", "Steals Per Game": "2.1", "Blocks Per Game": "0.2", "Field Goal Percentage": ".472", "3-Point Field Goal Percentage": ".369", "Free Throw Percentage": ".870", "Win Shares": "205.1", "Win Shares Per 48 Minutes": ".236"}, {"Rank": "91", "Player": "Bailey Howell", "From": "1960", "To": "1971", "Games": "950", "Minutes Played Per Game": "32.2", "Points Per Game": "18.7", "Total Rebounds Per Game": "9.9", "Assists Per Game": "2.0", "Steals Per Game": "", "Blocks Per Game": "", "Field Goal Percentage": ".480", "3-Point Field Goal Percentage": "", "Free Throw Percentage": ".762", "Win Shares": "114.8", "Win Shares Per 48 Minutes": ".180"}, {"Rank": "92", "Player": "Bob Lanier", "From": "1971", "To": "1984", "Games": "959", "Minutes Played Per Game": "33.5", "Points Per Game": "20.1", "Total Rebounds Per Game": "10.1", "Assists Per Game": "3.1", "Steals Per Game": "1.1", "Blocks Per Game": "1.5", "Field Goal Percentage": ".514", "3-Point Field Goal Percentage": "", "Free Throw Percentage": ".767", "Win Shares": "117.1", "Win Shares Per 48 Minutes": ".175"}, {"Rank": "93", "Player": "Kevin Johnson", "From": "1988", "To": "2000", "Games": "735", "Minutes Played Per Game": "34.1", "Points Per Game": "17.9", "Total Rebounds Per Game": "3.3", "Assists Per Game": "9.1", "Steals Per Game": "1.5", "Blocks Per Game": "0.2", "Field Goal Percentage": ".493", "3-Point Field Goal Percentage": ".305", "Free Throw Percentage": ".841", "Win Shares": "92.8", "Win Shares Per 48 Minutes": ".178"}, {"Rank": "94", "Player": "Jack Twyman", "From": "1956", "To": "1966", "Games": "823", "Minutes Played Per Game": "31.8", "Points Per Game": "19.2", "Total Rebounds Per Game": "6.6", "Assists Per Game": "2.3", "Steals Per Game": "", "Blocks Per Game": "", "Field Goal Percentage": ".450", "3-Point Field Goal Percentage": "", "Free Throw Percentage": ".778", "Win Shares": "75.0", "Win Shares Per 48 Minutes": ".138"}, {"Rank": "95", "Player": "Jo Jo White", "From": "1970", "To": "1981", "Games": "837", "Minutes Played Per Game": "35.8", "Points Per Game": "17.2", "Total Rebounds Per Game": "4.0", "Assists Per Game": "4.9", "Steals Per Game": "1.3", "Blocks Per Game": "0.2", "Field Goal Percentage": ".444", "3-Point Field Goal Percentage": "", "Free Throw Percentage": ".834", "Win Shares": "54.0", "Win Shares Per 48 Minutes": ".087"}, {"Rank": "96", "Player": "Tom Chambers", "From": "1982", "To": "1998", "Games": "1107", "Minutes Played Per Game": "30.6", "Points Per Game": "18.1", "Total Rebounds Per Game": "6.1", "Assists Per Game": "2.1", "Steals Per Game": "0.8", "Blocks Per Game": "0.6", "Field Goal Percentage": ".468", "3-Point Field Goal Percentage": ".307", "Free Throw Percentage": ".807", "Win Shares": "79.0", "Win Shares Per 48 Minutes": ".112"}]